lenspyx/__init__.py
lenspyx/_version.py
lenspyx/angles.py
lenspyx/approximator.py
lenspyx/cachers.py
lenspyx/lensing.py
lenspyx/sims.py
lenspyx/utils.py
lenspyx/utils_hp.py
lenspyx/remapping/__init__.py
lenspyx/remapping/deflection.py
lenspyx/remapping/deflection_028.py
lenspyx/remapping/deflection_029.py
lenspyx/remapping/utils_angles.py
lenspyx/remapping/utils_geom.py
lenspyx/tests/2829.py
lenspyx/tests/__init__.py
lenspyx/tests/aliasing.py
lenspyx/tests/anglesatpoles.py
lenspyx/tests/cmplxvsreal.py
lenspyx/tests/fibonacci.py
lenspyx/tests/gclm2lenmap.py
lenspyx/tests/helper.py
lenspyx/tests/lensaliasing.py
lenspyx/tests/lensgclm.py
lenspyx/tests/lensing.py
lenspyx/tests/nhl.py
lenspyx/tests/polrot.py
lenspyx/tests/qresp.py
lenspyx/tests/splits.py
lenspyx/tests/strongscal_bwd.py
lenspyx/tests/strongscal_fwd.py
lenspyx/tests/test_A.py
lenspyx/tests/test_FFP10fwd.py
lenspyx/tests/test_epsilon.py
lenspyx/tests/test_funkypointing.py
lenspyx/tests/test_nocurlshts.py
lenspyx/tests/theta_interpol.py
lenspyx/tests/u2nu.py
lenspyx/wigners/__init__.py
lenspyx/wigners/utils_wigners.py
lenspyx/wigners/wigners.py
lenspyx-2.0.52.data/data/lenspyx/data/cls/FFP10_wdipole_lensedCls.dat
lenspyx-2.0.52.data/data/lenspyx/data/cls/FFP10_wdipole_lenspotentialCls.dat
lenspyx-2.0.52.dist-info/LICENSE.txt
lenspyx-2.0.52.dist-info/METADATA
lenspyx-2.0.52.dist-info/WHEEL
lenspyx-2.0.52.dist-info/top_level.txt
lenspyx-2.0.52.dist-info/RECORD
