Metadata-Version: 2.1
Name: lenspyx
Version: 2.0.52
Summary: lensed CMB sims pipe
Home-page: https://github.com/carronj/lenspyx
Author: Julien Carron
Author-email: to.jcarron@gmail.com
License-File: LICENSE.txt
Requires-Dist: ducc0
